test/__init__.py
test/test_equipped.py
test/test_workerpool.py
workerpool/QueueWrapper.py
workerpool/__init__.py
workerpool/exceptions.py
workerpool/jobs.py
workerpool/pools.py
workerpool/workers.py
workerpool3-0.9.6.dist-info/licenses/LICENSE
workerpool3-0.9.6.dist-info/METADATA
workerpool3-0.9.6.dist-info/WHEEL
workerpool3-0.9.6.dist-info/top_level.txt
workerpool3-0.9.6.dist-info/RECORD
