Metadata-Version: 2.4
Name: workerpool3
Version: 0.9.6
Summary: Module for distributing jobs to a pool of worker threads.
Home-page: https://github.com/poipoii/workerpool
Author: Andrey Petrov
Author-email: andrey.petrov@shazow.net
License: MIT
Keywords: pooling threading jobs
Classifier: Intended Audience :: Developers
Classifier: Programming Language :: Python :: 3.10
Classifier: Programming Language :: Python :: 3.11
Classifier: Programming Language :: Python :: 3.12
Classifier: Topic :: Software Development :: Libraries :: Python Modules
Classifier: License :: OSI Approved :: MIT License
Classifier: Operating System :: OS Independent
License-File: LICENSE
Requires-Dist: six
Dynamic: author
Dynamic: author-email
Dynamic: classifier
Dynamic: description
Dynamic: home-page
Dynamic: keywords
Dynamic: license
Dynamic: license-file
Dynamic: requires-dist
Dynamic: summary
